{
  "best_metric": null,
  "best_model_checkpoint": null,
  "epoch": 4.979253112033195,
  "eval_steps": 500,
  "global_step": 150,
  "is_hyper_param_search": false,
  "is_local_process_zero": true,
  "is_world_process_zero": true,
  "log_history": [
    {
      "epoch": 0.33195020746887965,
      "grad_norm": 22.953773498535156,
      "learning_rate": 0.0001,
      "loss": -1.7123,
      "step": 10
    },
    {
      "epoch": 0.6639004149377593,
      "grad_norm": 48.58048629760742,
      "learning_rate": 0.0001,
      "loss": -2.1985,
      "step": 20
    },
    {
      "epoch": 0.995850622406639,
      "grad_norm": 84.67326354980469,
      "learning_rate": 0.0001,
      "loss": -3.3091,
      "step": 30
    },
    {
      "epoch": 1.3278008298755186,
      "grad_norm": 91.2318344116211,
      "learning_rate": 0.0001,
      "loss": -4.7542,
      "step": 40
    },
    {
      "epoch": 1.6597510373443982,
      "grad_norm": 144.8393096923828,
      "learning_rate": 0.0001,
      "loss": -7.3384,
      "step": 50
    },
    {
      "epoch": 1.991701244813278,
      "grad_norm": 191.4683837890625,
      "learning_rate": 0.0001,
      "loss": -10.2938,
      "step": 60
    },
    {
      "epoch": 2.323651452282158,
      "grad_norm": 162.60218811035156,
      "learning_rate": 0.0001,
      "loss": -14.5671,
      "step": 70
    },
    {
      "epoch": 2.6556016597510372,
      "grad_norm": 259.5569763183594,
      "learning_rate": 0.0001,
      "loss": -20.0701,
      "step": 80
    },
    {
      "epoch": 2.987551867219917,
      "grad_norm": 244.22802734375,
      "learning_rate": 0.0001,
      "loss": -27.4822,
      "step": 90
    },
    {
      "epoch": 3.3195020746887964,
      "grad_norm": 368.6877136230469,
      "learning_rate": 0.0001,
      "loss": -36.7562,
      "step": 100
    },
    {
      "epoch": 3.6514522821576763,
      "grad_norm": 421.7644348144531,
      "learning_rate": 0.0001,
      "loss": -47.3977,
      "step": 110
    },
    {
      "epoch": 3.983402489626556,
      "grad_norm": 418.7761535644531,
      "learning_rate": 0.0001,
      "loss": -62.1915,
      "step": 120
    },
    {
      "epoch": 4.3153526970954355,
      "grad_norm": 379.3583679199219,
      "learning_rate": 0.0001,
      "loss": -75.0956,
      "step": 130
    },
    {
      "epoch": 4.647302904564316,
      "grad_norm": 533.3359375,
      "learning_rate": 0.0001,
      "loss": -90.5641,
      "step": 140
    },
    {
      "epoch": 4.979253112033195,
      "grad_norm": 621.9202880859375,
      "learning_rate": 0.0001,
      "loss": -113.7458,
      "step": 150
    },
    {
      "epoch": 4.979253112033195,
      "step": 150,
      "total_flos": 0.0,
      "train_loss": -34.498444900512695,
      "train_runtime": 477.2351,
      "train_samples_per_second": 10.1,
      "train_steps_per_second": 0.314
    }
  ],
  "logging_steps": 10,
  "max_steps": 150,
  "num_input_tokens_seen": 0,
  "num_train_epochs": 5,
  "save_steps": 500,
  "stateful_callbacks": {
    "TrainerControl": {
      "args": {
        "should_epoch_stop": false,
        "should_evaluate": false,
        "should_log": false,
        "should_save": false,
        "should_training_stop": false
      },
      "attributes": {}
    }
  },
  "total_flos": 0.0,
  "train_batch_size": 1,
  "trial_name": null,
  "trial_params": null
}
